mcp2tcp/__init__.py
mcp2tcp/server.py
mcp2tcp-0.3.0.dist-info/METADATA
mcp2tcp-0.3.0.dist-info/WHEEL
mcp2tcp-0.3.0.dist-info/entry_points.txt
mcp2tcp-0.3.0.dist-info/licenses/LICENSE
mcp2tcp-0.3.0.dist-info/RECORD
